mem.cpython-37m-darwin.so
runmetal/Metal.py
runmetal/MetalKit.py
runmetal/__init__.py
runmetal/main.py
runmetal/pymetal.py
runmetal-0.1.dist-info/METADATA
runmetal-0.1.dist-info/WHEEL
runmetal-0.1.dist-info/entry_points.txt
runmetal-0.1.dist-info/top_level.txt
runmetal-0.1.dist-info/RECORD
