Metadata-Version: 2.1
Name: runmetal
Version: 0.1
Summary: run Apple Metal framework
Home-page: https://github.com/wtnb75/runmetal
Author: Takashi WATANABE
Author-email: wtnb75@gmail.com
License: MIT
Keywords: apple metal gpu
Platform: UNKNOWN
Classifier: Development Status :: 3 - Alpha
Classifier: License :: OSI Approved :: MIT License
Classifier: Topic :: Software Development
Classifier: Programming Language :: Python :: 3
Requires-Python: >=3
Requires-Dist: PyYAML
Requires-Dist: click
Requires-Dist: pyobjc
Requires-Dist: numpy
